pyflann_ibeis/__init__.py
pyflann_ibeis/__main__.py
pyflann_ibeis/__main__.pyi
pyflann_ibeis/exceptions.py
pyflann_ibeis/exceptions.pyi
pyflann_ibeis/flann_ctypes.py
pyflann_ibeis/flann_ctypes.pyi
pyflann_ibeis/index.py
pyflann_ibeis/index.pyi
pyflann_ibeis/py.typed
pyflann_ibeis/lib/__init__.py
pyflann_ibeis/lib/libflann.so
pyflann_ibeis/lib/libflann.so.2.4
pyflann_ibeis/lib/libflann.so.2.4.2
pyflann_ibeis/lib/libflann_cpp.so
pyflann_ibeis/lib/libflann_cpp.so.2.4
pyflann_ibeis/lib/libflann_cpp.so.2.4.2
pyflann_ibeis/lib/libflann_cpp_s.a
pyflann_ibeis/lib/libflann_s.a
pyflann_ibeis.libs/libgomp-e985bcbb.so.1.0.0
pyflann_ibeis.libs/liblz4-c23f16fe.so.1.8.3
pyflann_ibeis-2.4.2.dist-info/METADATA
pyflann_ibeis-2.4.2.dist-info/WHEEL
pyflann_ibeis-2.4.2.dist-info/top_level.txt
pyflann_ibeis-2.4.2.dist-info/RECORD
pyflann_ibeis-2.4.2.dist-info/licenses/COPYING
pyflann_ibeis-2.4.2.dist-info/sboms/auditwheel.cdx.json
