Metadata-Version: 2.4
Name: pyflann_ibeis
Version: 2.4.2
Summary: FLANN (for IBEIS) - Fast Library for Approximate Nearest Neighbors
Home-page: https://github.com/Erotemic/pyflann_ibeis
Author: Jon Crall, Marius Muja
Author-email: erotemic@gmail.com
License: BSD
Classifier: Development Status :: 6 - Mature
Classifier: License :: OSI Approved :: BSD License
Classifier: Intended Audience :: Developers
Classifier: Intended Audience :: Science/Research
Classifier: Operating System :: Unix
Classifier: Topic :: Software Development :: Libraries :: Python Modules
Classifier: Programming Language :: Python :: 3.9
Classifier: Programming Language :: Python :: 3.10
Classifier: Programming Language :: Python :: 3.11
Classifier: Programming Language :: Python :: 3.12
Classifier: Programming Language :: Python :: 3.13
Classifier: Topic :: Scientific/Engineering :: Artificial Intelligence
Classifier: Topic :: Scientific/Engineering :: Image Recognition
Requires-Python: >=3.8
License-File: COPYING
Requires-Dist: numpy>=2.1.0; python_version < "4.0" and python_version >= "3.13"
Requires-Dist: numpy>=1.26.0; python_version < "3.13" and python_version >= "3.12"
Requires-Dist: numpy>=1.23.2; python_version < "3.12" and python_version >= "3.11"
Requires-Dist: numpy>=1.21.6; python_version < "3.11" and python_version >= "3.10"
Requires-Dist: numpy>=1.19.3; python_version < "3.10" and python_version >= "3.9"
Requires-Dist: numpy>=1.19.3; python_version < "3.9" and python_version >= "3.8"
Provides-Extra: all
Requires-Dist: numpy>=2.1.0; (python_version < "4.0" and python_version >= "3.13") and extra == "all"
Requires-Dist: numpy>=1.26.0; (python_version < "3.13" and python_version >= "3.12") and extra == "all"
Requires-Dist: numpy>=1.23.2; (python_version < "3.12" and python_version >= "3.11") and extra == "all"
Requires-Dist: numpy>=1.21.6; (python_version < "3.11" and python_version >= "3.10") and extra == "all"
Requires-Dist: numpy>=1.19.3; (python_version < "3.10" and python_version >= "3.9") and extra == "all"
Requires-Dist: numpy>=1.19.3; (python_version < "3.9" and python_version >= "3.8") and extra == "all"
Requires-Dist: xdoctest>=1.1.3; extra == "all"
Requires-Dist: ubelt>=1.3.4; extra == "all"
Requires-Dist: pytest>=6.2.5; python_version >= "3.10.0" and extra == "all"
Requires-Dist: pytest>=4.6.0; (python_version < "3.10.0" and python_version >= "3.7.0") and extra == "all"
Requires-Dist: pytest>=4.6.0; (python_version < "3.7.0" and python_version >= "3.6.0") and extra == "all"
Requires-Dist: pytest<=6.1.2,>=4.6.0; (python_version < "3.6.0" and python_version >= "3.5.0") and extra == "all"
Requires-Dist: pytest<=4.6.11,>=4.6.0; (python_version < "3.5.0" and python_version >= "3.4.0") and extra == "all"
Requires-Dist: pytest<=4.6.11,>=4.6.0; (python_version < "2.8.0" and python_version >= "2.7.0") and extra == "all"
Requires-Dist: pytest-cov>=3.0.0; python_version >= "3.6.0" and extra == "all"
Requires-Dist: pytest-cov>=2.9.0; (python_version < "3.6.0" and python_version >= "3.5.0") and extra == "all"
Requires-Dist: pytest-cov>=2.8.1; (python_version < "3.5.0" and python_version >= "3.4.0") and extra == "all"
Requires-Dist: pytest-cov>=2.8.1; (python_version < "2.8.0" and python_version >= "2.7.0") and extra == "all"
Requires-Dist: coverage>=7.0.0; (python_version < "4.0" and python_version >= "3.11") and extra == "all"
Requires-Dist: coverage>=6.1.1; (python_version < "3.11" and python_version >= "3.10") and extra == "all"
Requires-Dist: coverage>=5.3.1; (python_version < "3.10" and python_version >= "3.9") and extra == "all"
Requires-Dist: coverage>=6.1.1; (python_version < "3.9" and python_version >= "3.8") and extra == "all"
Requires-Dist: coverage>=6.1.1; (python_version < "3.8" and python_version >= "3.7") and extra == "all"
Requires-Dist: coverage>=6.1.1; (python_version < "3.7" and python_version >= "3.6") and extra == "all"
Requires-Dist: coverage>=5.3.1; (python_version < "3.6" and python_version >= "3.5") and extra == "all"
Requires-Dist: coverage>=4.3.4; (python_version < "3.5" and python_version >= "3.4") and extra == "all"
Requires-Dist: coverage>=5.3.1; (python_version < "3.4" and python_version >= "2.7") and extra == "all"
Requires-Dist: coverage>=4.5; (python_version < "2.7" and python_version >= "2.6") and extra == "all"
Requires-Dist: cibuildwheel>=2.17.0; extra == "all"
Requires-Dist: scikit-build; extra == "all"
Requires-Dist: cmake; extra == "all"
Requires-Dist: ninja; extra == "all"
Provides-Extra: runtime
Requires-Dist: numpy>=2.1.0; (python_version < "4.0" and python_version >= "3.13") and extra == "runtime"
Requires-Dist: numpy>=1.26.0; (python_version < "3.13" and python_version >= "3.12") and extra == "runtime"
Requires-Dist: numpy>=1.23.2; (python_version < "3.12" and python_version >= "3.11") and extra == "runtime"
Requires-Dist: numpy>=1.21.6; (python_version < "3.11" and python_version >= "3.10") and extra == "runtime"
Requires-Dist: numpy>=1.19.3; (python_version < "3.10" and python_version >= "3.9") and extra == "runtime"
Requires-Dist: numpy>=1.19.3; (python_version < "3.9" and python_version >= "3.8") and extra == "runtime"
Provides-Extra: tests
Requires-Dist: xdoctest>=1.1.3; extra == "tests"
Requires-Dist: ubelt>=1.3.4; extra == "tests"
Requires-Dist: pytest>=6.2.5; python_version >= "3.10.0" and extra == "tests"
Requires-Dist: pytest>=4.6.0; (python_version < "3.10.0" and python_version >= "3.7.0") and extra == "tests"
Requires-Dist: pytest>=4.6.0; (python_version < "3.7.0" and python_version >= "3.6.0") and extra == "tests"
Requires-Dist: pytest<=6.1.2,>=4.6.0; (python_version < "3.6.0" and python_version >= "3.5.0") and extra == "tests"
Requires-Dist: pytest<=4.6.11,>=4.6.0; (python_version < "3.5.0" and python_version >= "3.4.0") and extra == "tests"
Requires-Dist: pytest<=4.6.11,>=4.6.0; (python_version < "2.8.0" and python_version >= "2.7.0") and extra == "tests"
Requires-Dist: pytest-cov>=3.0.0; python_version >= "3.6.0" and extra == "tests"
Requires-Dist: pytest-cov>=2.9.0; (python_version < "3.6.0" and python_version >= "3.5.0") and extra == "tests"
Requires-Dist: pytest-cov>=2.8.1; (python_version < "3.5.0" and python_version >= "3.4.0") and extra == "tests"
Requires-Dist: pytest-cov>=2.8.1; (python_version < "2.8.0" and python_version >= "2.7.0") and extra == "tests"
Requires-Dist: coverage>=7.0.0; (python_version < "4.0" and python_version >= "3.11") and extra == "tests"
Requires-Dist: coverage>=6.1.1; (python_version < "3.11" and python_version >= "3.10") and extra == "tests"
Requires-Dist: coverage>=5.3.1; (python_version < "3.10" and python_version >= "3.9") and extra == "tests"
Requires-Dist: coverage>=6.1.1; (python_version < "3.9" and python_version >= "3.8") and extra == "tests"
Requires-Dist: coverage>=6.1.1; (python_version < "3.8" and python_version >= "3.7") and extra == "tests"
Requires-Dist: coverage>=6.1.1; (python_version < "3.7" and python_version >= "3.6") and extra == "tests"
Requires-Dist: coverage>=5.3.1; (python_version < "3.6" and python_version >= "3.5") and extra == "tests"
Requires-Dist: coverage>=4.3.4; (python_version < "3.5" and python_version >= "3.4") and extra == "tests"
Requires-Dist: coverage>=5.3.1; (python_version < "3.4" and python_version >= "2.7") and extra == "tests"
Requires-Dist: coverage>=4.5; (python_version < "2.7" and python_version >= "2.6") and extra == "tests"
Provides-Extra: optional
Provides-Extra: build
Requires-Dist: cibuildwheel>=2.17.0; extra == "build"
Requires-Dist: scikit-build; extra == "build"
Requires-Dist: cmake; extra == "build"
Requires-Dist: ninja; extra == "build"
Provides-Extra: docs
Requires-Dist: sphinx>=5.0.1; extra == "docs"
Requires-Dist: sphinx-autobuild>=2021.3.14; extra == "docs"
Requires-Dist: sphinx_rtd_theme>=1.0.0; extra == "docs"
Requires-Dist: sphinxcontrib-napoleon>=0.7; extra == "docs"
Requires-Dist: sphinx-autoapi>=1.8.4; extra == "docs"
Requires-Dist: Pygments>=2.9.0; extra == "docs"
Requires-Dist: myst_parser>=0.18.0; extra == "docs"
Requires-Dist: sphinx-reredirects>=0.0.1; extra == "docs"
Provides-Extra: all-strict
Requires-Dist: numpy==2.1.0; (python_version < "4.0" and python_version >= "3.13") and extra == "all-strict"
Requires-Dist: numpy==1.26.0; (python_version < "3.13" and python_version >= "3.12") and extra == "all-strict"
Requires-Dist: numpy==1.23.2; (python_version < "3.12" and python_version >= "3.11") and extra == "all-strict"
Requires-Dist: numpy==1.21.6; (python_version < "3.11" and python_version >= "3.10") and extra == "all-strict"
Requires-Dist: numpy==1.19.3; (python_version < "3.10" and python_version >= "3.9") and extra == "all-strict"
Requires-Dist: numpy==1.19.3; (python_version < "3.9" and python_version >= "3.8") and extra == "all-strict"
Requires-Dist: xdoctest==1.1.3; extra == "all-strict"
Requires-Dist: ubelt==1.3.4; extra == "all-strict"
Requires-Dist: pytest==6.2.5; python_version >= "3.10.0" and extra == "all-strict"
Requires-Dist: pytest==4.6.0; (python_version < "3.10.0" and python_version >= "3.7.0") and extra == "all-strict"
Requires-Dist: pytest==4.6.0; (python_version < "3.7.0" and python_version >= "3.6.0") and extra == "all-strict"
Requires-Dist: pytest<=6.1.2,==4.6.0; (python_version < "3.6.0" and python_version >= "3.5.0") and extra == "all-strict"
Requires-Dist: pytest<=4.6.11,==4.6.0; (python_version < "3.5.0" and python_version >= "3.4.0") and extra == "all-strict"
Requires-Dist: pytest<=4.6.11,==4.6.0; (python_version < "2.8.0" and python_version >= "2.7.0") and extra == "all-strict"
Requires-Dist: pytest-cov==3.0.0; python_version >= "3.6.0" and extra == "all-strict"
Requires-Dist: pytest-cov==2.9.0; (python_version < "3.6.0" and python_version >= "3.5.0") and extra == "all-strict"
Requires-Dist: pytest-cov==2.8.1; (python_version < "3.5.0" and python_version >= "3.4.0") and extra == "all-strict"
Requires-Dist: pytest-cov==2.8.1; (python_version < "2.8.0" and python_version >= "2.7.0") and extra == "all-strict"
Requires-Dist: coverage==7.0.0; (python_version < "4.0" and python_version >= "3.11") and extra == "all-strict"
Requires-Dist: coverage==6.1.1; (python_version < "3.11" and python_version >= "3.10") and extra == "all-strict"
Requires-Dist: coverage==5.3.1; (python_version < "3.10" and python_version >= "3.9") and extra == "all-strict"
Requires-Dist: coverage==6.1.1; (python_version < "3.9" and python_version >= "3.8") and extra == "all-strict"
Requires-Dist: coverage==6.1.1; (python_version < "3.8" and python_version >= "3.7") and extra == "all-strict"
Requires-Dist: coverage==6.1.1; (python_version < "3.7" and python_version >= "3.6") and extra == "all-strict"
Requires-Dist: coverage==5.3.1; (python_version < "3.6" and python_version >= "3.5") and extra == "all-strict"
Requires-Dist: coverage==4.3.4; (python_version < "3.5" and python_version >= "3.4") and extra == "all-strict"
Requires-Dist: coverage==5.3.1; (python_version < "3.4" and python_version >= "2.7") and extra == "all-strict"
Requires-Dist: coverage==4.5; (python_version < "2.7" and python_version >= "2.6") and extra == "all-strict"
Requires-Dist: cibuildwheel==2.17.0; extra == "all-strict"
Requires-Dist: scikit-build; extra == "all-strict"
Requires-Dist: cmake; extra == "all-strict"
Requires-Dist: ninja; extra == "all-strict"
Provides-Extra: runtime-strict
Requires-Dist: numpy==2.1.0; (python_version < "4.0" and python_version >= "3.13") and extra == "runtime-strict"
Requires-Dist: numpy==1.26.0; (python_version < "3.13" and python_version >= "3.12") and extra == "runtime-strict"
Requires-Dist: numpy==1.23.2; (python_version < "3.12" and python_version >= "3.11") and extra == "runtime-strict"
Requires-Dist: numpy==1.21.6; (python_version < "3.11" and python_version >= "3.10") and extra == "runtime-strict"
Requires-Dist: numpy==1.19.3; (python_version < "3.10" and python_version >= "3.9") and extra == "runtime-strict"
Requires-Dist: numpy==1.19.3; (python_version < "3.9" and python_version >= "3.8") and extra == "runtime-strict"
Provides-Extra: tests-strict
Requires-Dist: xdoctest==1.1.3; extra == "tests-strict"
Requires-Dist: ubelt==1.3.4; extra == "tests-strict"
Requires-Dist: pytest==6.2.5; python_version >= "3.10.0" and extra == "tests-strict"
Requires-Dist: pytest==4.6.0; (python_version < "3.10.0" and python_version >= "3.7.0") and extra == "tests-strict"
Requires-Dist: pytest==4.6.0; (python_version < "3.7.0" and python_version >= "3.6.0") and extra == "tests-strict"
Requires-Dist: pytest<=6.1.2,==4.6.0; (python_version < "3.6.0" and python_version >= "3.5.0") and extra == "tests-strict"
Requires-Dist: pytest<=4.6.11,==4.6.0; (python_version < "3.5.0" and python_version >= "3.4.0") and extra == "tests-strict"
Requires-Dist: pytest<=4.6.11,==4.6.0; (python_version < "2.8.0" and python_version >= "2.7.0") and extra == "tests-strict"
Requires-Dist: pytest-cov==3.0.0; python_version >= "3.6.0" and extra == "tests-strict"
Requires-Dist: pytest-cov==2.9.0; (python_version < "3.6.0" and python_version >= "3.5.0") and extra == "tests-strict"
Requires-Dist: pytest-cov==2.8.1; (python_version < "3.5.0" and python_version >= "3.4.0") and extra == "tests-strict"
Requires-Dist: pytest-cov==2.8.1; (python_version < "2.8.0" and python_version >= "2.7.0") and extra == "tests-strict"
Requires-Dist: coverage==7.0.0; (python_version < "4.0" and python_version >= "3.11") and extra == "tests-strict"
Requires-Dist: coverage==6.1.1; (python_version < "3.11" and python_version >= "3.10") and extra == "tests-strict"
Requires-Dist: coverage==5.3.1; (python_version < "3.10" and python_version >= "3.9") and extra == "tests-strict"
Requires-Dist: coverage==6.1.1; (python_version < "3.9" and python_version >= "3.8") and extra == "tests-strict"
Requires-Dist: coverage==6.1.1; (python_version < "3.8" and python_version >= "3.7") and extra == "tests-strict"
Requires-Dist: coverage==6.1.1; (python_version < "3.7" and python_version >= "3.6") and extra == "tests-strict"
Requires-Dist: coverage==5.3.1; (python_version < "3.6" and python_version >= "3.5") and extra == "tests-strict"
Requires-Dist: coverage==4.3.4; (python_version < "3.5" and python_version >= "3.4") and extra == "tests-strict"
Requires-Dist: coverage==5.3.1; (python_version < "3.4" and python_version >= "2.7") and extra == "tests-strict"
Requires-Dist: coverage==4.5; (python_version < "2.7" and python_version >= "2.6") and extra == "tests-strict"
Provides-Extra: optional-strict
Provides-Extra: build-strict
Requires-Dist: cibuildwheel==2.17.0; extra == "build-strict"
Requires-Dist: scikit-build; extra == "build-strict"
Requires-Dist: cmake; extra == "build-strict"
Requires-Dist: ninja; extra == "build-strict"
Provides-Extra: docs-strict
Requires-Dist: sphinx==5.0.1; extra == "docs-strict"
Requires-Dist: sphinx-autobuild==2021.3.14; extra == "docs-strict"
Requires-Dist: sphinx_rtd_theme==1.0.0; extra == "docs-strict"
Requires-Dist: sphinxcontrib-napoleon==0.7; extra == "docs-strict"
Requires-Dist: sphinx-autoapi==1.8.4; extra == "docs-strict"
Requires-Dist: Pygments==2.9.0; extra == "docs-strict"
Requires-Dist: myst_parser==0.18.0; extra == "docs-strict"
Requires-Dist: sphinx-reredirects==0.0.1; extra == "docs-strict"
Dynamic: author
Dynamic: author-email
Dynamic: classifier
Dynamic: description
Dynamic: description-content-type
Dynamic: home-page
Dynamic: license
Dynamic: license-file
Dynamic: provides-extra
Dynamic: requires-dist
Dynamic: requires-python
Dynamic: summary
